MDML/MDML.py
MDML/__init__.py
MDML/utils.py
code/__init__.py
code/scMDML.py
scMDML/__init__.py
scMDML/scMDML.py
scmdml/__init__.py
scmdml/scMDML.py
scmdml-2.8.dist-info/LICENSE
scmdml-2.8.dist-info/METADATA
scmdml-2.8.dist-info/WHEEL
scmdml-2.8.dist-info/top_level.txt
scmdml-2.8.dist-info/RECORD
